streetview_dl/__init__.py
streetview_dl/auth.py
streetview_dl/cli.py
streetview_dl/core.py
streetview_dl/metadata.py
streetview_dl/processing.py
streetview_dl/utils.py
streetview_dl-0.6.0.dist-info/licenses/LICENSE
streetview_dl-0.6.0.dist-info/METADATA
streetview_dl-0.6.0.dist-info/WHEEL
streetview_dl-0.6.0.dist-info/entry_points.txt
streetview_dl-0.6.0.dist-info/top_level.txt
streetview_dl-0.6.0.dist-info/RECORD
