Metadata-Version: 2.4
Name: streetview-dl
Version: 0.6.0
Summary: Download high-resolution Google Street View panoramas from the command line
Author-email: Your Name <mattstiles@gmail.com>
License: MIT
Project-URL: Homepage, https://github.com/yourusername/streetview-dl
Project-URL: Repository, https://github.com/yourusername/streetview-dl
Project-URL: Documentation, https://github.com/yourusername/streetview-dl#readme
Project-URL: Changelog, https://github.com/yourusername/streetview-dl/blob/main/CHANGELOG.md
Project-URL: Bug Tracker, https://github.com/yourusername/streetview-dl/issues
Keywords: streetview,panorama,google-maps,cli,imagery,python
Classifier: Development Status :: 4 - Beta
Classifier: Environment :: Console
Classifier: Intended Audience :: Developers
Classifier: Intended Audience :: End Users/Desktop
Classifier: License :: OSI Approved :: MIT License
Classifier: Operating System :: OS Independent
Classifier: Programming Language :: Python :: 3
Classifier: Programming Language :: Python :: 3.8
Classifier: Programming Language :: Python :: 3.9
Classifier: Programming Language :: Python :: 3.10
Classifier: Programming Language :: Python :: 3.11
Classifier: Programming Language :: Python :: 3.12
Classifier: Topic :: Internet :: WWW/HTTP
Classifier: Topic :: Multimedia :: Graphics
Classifier: Topic :: Software Development :: Libraries :: Python Modules
Classifier: Topic :: System :: Archiving
Classifier: Topic :: Utilities
Requires-Python: >=3.8
License-File: LICENSE
Requires-Dist: click>=8.0.0
Requires-Dist: requests>=2.25.0
Requires-Dist: Pillow>=9.0.0
Requires-Dist: rich>=12.0.0
Requires-Dist: pydantic>=2.0.0
Provides-Extra: dev
Requires-Dist: pytest>=7.0.0; extra == "dev"
Requires-Dist: pytest-cov>=4.0.0; extra == "dev"
Requires-Dist: black>=22.0.0; extra == "dev"
Requires-Dist: flake8>=5.0.0; extra == "dev"
Requires-Dist: mypy>=1.0.0; extra == "dev"
Requires-Dist: build>=0.8.0; extra == "dev"
Requires-Dist: twine>=4.0.0; extra == "dev"
Dynamic: license-file
